open_news/__init__.py
open_news/google/__init__.py
open_news/google/_parser.py
open_news/google/article.py
open_news/google/constant.py
open_news/google/log.py
open_news/google/request.py
open_news/google/feed/__init__.py
open_news/google/feed/_util.py
open_news/google/feed/article.py
open_news/google/feed/channel.py
open_news/google/feed/exception.py
open_news/google/feed/item.py
py_open_news-0.0.11.dist-info/licenses/LICENSE
py_open_news-0.0.11.dist-info/METADATA
py_open_news-0.0.11.dist-info/WHEEL
py_open_news-0.0.11.dist-info/top_level.txt
py_open_news-0.0.11.dist-info/RECORD
