Metadata-Version: 2.4
Name: py-open-news
Version: 0.0.11
Summary: Get free news for our little project
Author-email: "Shin-Hong Chen(Ted)" <imaging8896@gmail.com>
Maintainer-email: "Shin-Hong Chen(Ted)" <imaging8896@gmail.com>
License: MIT License
Project-URL: Repository, https://github.com/imaging8896/open-news
Keywords: news
Classifier: Development Status :: 1 - Planning
Classifier: Environment :: Web Environment
Classifier: Framework :: Scrapy
Classifier: Intended Audience :: Developers
Classifier: Intended Audience :: Information Technology
Classifier: Topic :: Internet :: WWW/HTTP
Classifier: Topic :: Internet :: WWW/HTTP :: Dynamic Content :: News/Diary
Classifier: Topic :: Software Development :: Libraries
Classifier: Topic :: Software Development :: Libraries :: Python Modules
Classifier: License :: OSI Approved :: MIT License
Classifier: Programming Language :: Python
Classifier: Programming Language :: Python :: 3
Classifier: Programming Language :: Python :: 3.10
Classifier: Programming Language :: Python :: 3.11
Classifier: Programming Language :: Python :: 3.12
Classifier: Programming Language :: Python :: 3.13
Requires-Python: >=3.10
License-File: LICENSE
Requires-Dist: cloudscraper
Requires-Dist: curl_cffi
Dynamic: license-file
